{
    "Version": "1.2",
    "Data": {
        "Source": "c:\\gitstudy\\hw07\\hw07\\intermediate\\build\\win64\\x64\\unrealeditor\\development\\hw07\\permoduleinline.gen.cpp",
        "ProvidedModule": "",
        "PCH": "c:\\gitstudy\\hw07\\hw07\\intermediate\\build\\win64\\x64\\hw07editor\\development\\unrealed\\sharedpch.unrealed.project.valapi.cpp20.h.pch",
        "Includes": [
            "c:\\gitstudy\\hw07\\hw07\\intermediate\\build\\win64\\x64\\unrealeditor\\development\\hw07\\definitions.hw07.h",
            "c:\\program files\\epic games\\ue_5.5\\engine\\source\\runtime\\core\\public\\hal\\permoduleinline.inl"
        ],
        "ImportedModules": [],
        "ImportedHeaderUnits": []
    }
}